LICENSE.txt
README.md
setup.cfg
setup.py
netbluemind/__init__.py
netbluemind/addressbook/__init__.py
netbluemind/addressbook/api/AddressBookDescriptor.py
netbluemind/addressbook/api/CertInfo.py
netbluemind/addressbook/api/CertInfoCertUsage.py
netbluemind/addressbook/api/IAddressBook.py
netbluemind/addressbook/api/IAddressBookUids.py
netbluemind/addressbook/api/IAddressBooks.py
netbluemind/addressbook/api/IAddressBooksMgmt.py
netbluemind/addressbook/api/IVCardService.py
netbluemind/addressbook/api/VCard.py
netbluemind/addressbook/api/VCardBasicAttribute.py
netbluemind/addressbook/api/VCardChanges.py
netbluemind/addressbook/api/VCardChangesItemAdd.py
netbluemind/addressbook/api/VCardChangesItemDelete.py
netbluemind/addressbook/api/VCardChangesItemModify.py
netbluemind/addressbook/api/VCardCommunications.py
netbluemind/addressbook/api/VCardCommunicationsEmail.py
netbluemind/addressbook/api/VCardCommunicationsImpp.py
netbluemind/addressbook/api/VCardCommunicationsLang.py
netbluemind/addressbook/api/VCardCommunicationsTel.py
netbluemind/addressbook/api/VCardDeliveryAddressing.py
netbluemind/addressbook/api/VCardDeliveryAddressingAddress.py
netbluemind/addressbook/api/VCardExplanatory.py
netbluemind/addressbook/api/VCardExplanatoryUrl.py
netbluemind/addressbook/api/VCardIdentification.py
netbluemind/addressbook/api/VCardIdentificationFormatedName.py
netbluemind/addressbook/api/VCardIdentificationGender.py
netbluemind/addressbook/api/VCardIdentificationName.py
netbluemind/addressbook/api/VCardIdentificationNickname.py
netbluemind/addressbook/api/VCardInfo.py
netbluemind/addressbook/api/VCardKind.py
netbluemind/addressbook/api/VCardOrganizational.py
netbluemind/addressbook/api/VCardOrganizationalMember.py
netbluemind/addressbook/api/VCardOrganizationalOrg.py
netbluemind/addressbook/api/VCardParameter.py
netbluemind/addressbook/api/VCardQuery.py
netbluemind/addressbook/api/VCardQueryOrderBy.py
netbluemind/addressbook/api/VCardRelated.py
netbluemind5.egg-info/PKG-INFO
netbluemind5.egg-info/SOURCES.txt
netbluemind5.egg-info/dependency_links.txt
netbluemind5.egg-info/requires.txt
netbluemind5.egg-info/top_level.txt