Metadata-Version: 2.1
Name: netbluemind5
Version: 5.5.3158
Summary: Automatically generated client for BlueMind >= 5 REST API. Check netbluemind4 for older releases
Home-page: http://gitlab.bluemind.net/
Author: BlueMind team
Author-email: contact@bluemind.net
Keywords: bluemind,rest,api,mail,groupware
Classifier: Development Status :: 5 - Production/Stable
Classifier: Intended Audience :: Developers
Classifier: Programming Language :: Python :: 3
License-File: LICENSE.txt
